vmat/__init__.py
vmat/_walkpkg.py
vmat/vapp.py
vmat/vask.py
vmat/vath.py
vmat/vickle.py
vmat/vicom.py
vmat/view.py
vmat/vimage.py
vmat/vpoly.py
vmat/vprop.py
vmat/vrc.py
vmat/example/__init__.py
vmat/example/image_reslice.py
vmat/example/interaction_box.py
vmat/example/read_dicom_slice_view.py
vmat/example/surface_volume_rendering.py
vmat-0.0.7.dist-info/METADATA
vmat-0.0.7.dist-info/WHEEL
vmat-0.0.7.dist-info/top_level.txt
vmat-0.0.7.dist-info/RECORD
